allie/__init__.py
allie/allie.py
tdc-0.1.dist-info/METADATA
tdc-0.1.dist-info/RECORD
tdc-0.1.dist-info/WHEEL
tdc-0.1.dist-info/top_level.txt
